pylat/__init__.py
pylat/exceptions.py
pylat/evaluation/__init__.py
pylat/evaluation/metrics.py
pylat/evaluation/stats.py
pylat/neuralnet/__init__.py
pylat/neuralnet/embeddings.py
pylat/neuralnet/layers.py
pylat/neuralnet/model.py
pylat/neuralnet/trainer.py
pylat/neuralnet/utils.py
pylat/neuralnet/rnn/__init__.py
pylat/neuralnet/rnn/cells.py
pylat/neuralnet/rnn/layers.py
pylat/neuralnet/rnn/recurrent_neural_network.py
pylat/wrapper/__init__.py
pylat/wrapper/predictor/RNNWrapper.py
pylat/wrapper/predictor/__init__.py
pylat/wrapper/transformer/__init__.py
pylat/wrapper/transformer/attributes_adder.py
pylat/wrapper/transformer/dataframe_selector.py
pylat/wrapper/transformer/embeddings_transformer.py
pylat/wrapper/transformer/lexicon_manager.py
pylat/wrapper/transformer/sentence_padder.py
pylat/wrapper/transformer/text_preprocessor.py
pylat/wrapper/transformer/to_array.py
pylat-0.2.1.dist-info/METADATA
pylat-0.2.1.dist-info/RECORD
pylat-0.2.1.dist-info/WHEEL
pylat-0.2.1.dist-info/dependency_links.txt
pylat-0.2.1.dist-info/top_level.txt
