Metadata-Version: 2.1
Name: pylat
Version: 0.2.1
Summary: A simple library with some common nlp operations
Home-page: https://github.com/weso/pylat
Author: Alejandro González Hevia
Author-email: alejandrgh11@gmail.com
License: GPL-3.0
Platform: UNKNOWN
Requires-Dist: gensim
Requires-Dist: scikit-learn
Requires-Dist: numpy
Requires-Dist: pandas
Requires-Dist: spacy (==2.0.18)
Requires-Dist: tensorflow (==1.13.1)
Requires-Dist: xmltodict
Requires-Dist: en-core-web-sm
Requires-Dist: es-core-news-sm
